{"updatedAt":"2026-07-10T20:00:15+09:00","marketStatus":"CLOSE","status":{"ok":true,"errors":[]},"themes":[{"no":373,"name":"5G(5세대 이동통신)","score":90.7,"aliases":["광통신(광케이블/광섬유 등)"],"changeRate":8.33,"rise":47,"steady":2,"fall":5,"total":54,"tradingValueEok":72332.1,"streakDays":2,"recent3d":-1.89,"capCount":2,"naverLeaders":[{"code":"049080","name":"기가레인","rate":29.92},{"code":"069540","name":"빛과전자","rate":29.89}],"judeokLeaders":[{"code":"010170","name":"대한광통신","price":12600,"rate":18.31,"tvEok":3833.07,"capEok":19591.0,"isCap":false,"prevClose":10650,"open":null,"high":null,"low":null,"nxt":null,"ot":null,"isBigTv":true},{"code":"007660","name":"이수페타시스","price":103800,"rate":13.07,"tvEok":1712.94,"capEok":76199.0,"isCap":false,"prevClose":91802,"open":null,"high":null,"low":null,"nxt":null,"ot":null,"isBigTv":true},{"code":"178320","name":"서진시스템","price":47350,"rate":13.55,"tvEok":529.83,"capEok":30139.0,"isCap":false,"prevClose":41700,"open":null,"high":null,"low":null,"nxt":null,"ot":null,"isBigTv":false}],"stocks":[{"code":"049080","name":"기가레인","price":5970,"rate":29.92,"tvEok":20.45,"capEok":507.0,"isCap":true,"prevClose":4595,"open":4700,"high":5970,"low":4695,"nxt":null,"ot":{"price":5970,"rate":0.0}},{"code":"069540","name":"빛과전자","price":2325,"rate":29.89,"tvEok":151.37,"capEok":2620.0,"isCap":true,"prevClose":1790,"open":1825,"high":2325,"low":1825,"nxt":null,"ot":{"price":2325,"rate":0.0}},{"code":"065770","name":"CS","price":1815,"rate":20.2,"tvEok":21.85,"capEok":176.0,"isCap":false,"prevClose":1510,"open":1537,"high":1859,"low":1510,"nxt":null,"ot":{"price":1789,"rate":-1.43}},{"code":"010170","name":"대한광통신","price":12600,"rate":18.31,"tvEok":3833.07,"capEok":19591.0,"isCap":false,"prevClose":10650,"open":11110,"high":13550,"low":11090,"nxt":null,"ot":{"price":12300,"rate":-2.38}}]},{"no":287,"name":"PCB(FPCB 등)","score":88.3,"aliases":["반도체 기판(FC-BGA/PCB/MLB 등)","우주항공산업(누리호/인공위성 등)"],"changeRate":8.3,"rise":31,"steady":0,"fall":0,"total":31,"tradingValueEok":20675.5,"streakDays":2,"recent3d":-2.79,"capCount":1,"naverLeaders":[{"code":"015260","name":"에이엔피","rate":29.9},{"code":"085910","name":"네오티스","rate":19.18}],"judeokLeaders":[{"code":"007660","name":"이수페타시스","price":103800,"rate":13.07,"tvEok":1712.94,"capEok":76199.0,"isCap":false,"prevClose":91802,"open":null,"high":null,"low":null,"nxt":null,"ot":null,"isBigTv":true},{"code":"085910","name":"네오티스","price":17960,"rate":19.18,"tvEok":70.62,"capEok":2478.0,"isCap":false,"prevClose":15070,"open":null,"high":null,"low":null,"nxt":null,"ot":null,"isBigTv":false},{"code":"356860","name":"티엘비","price":75200,"rate":9.46,"tvEok":186.39,"capEok":7394.0,"isCap":false,"prevClose":68701,"open":null,"high":null,"low":null,"nxt":null,"ot":null,"isBigTv":false}],"stocks":[{"code":"015260","name":"에이엔피","price":378,"rate":29.9,"tvEok":6.37,"capEok":178.0,"isCap":true,"prevClose":291,"open":291,"high":378,"low":291,"nxt":null,"ot":{"price":378,"rate":0.0}},{"code":"085910","name":"네오티스","price":17960,"rate":19.18,"tvEok":70.62,"capEok":2478.0,"isCap":false,"prevClose":15070,"open":15070,"high":18710,"low":14500,"nxt":null,"ot":{"price":17960,"rate":0.0}},{"code":"168360","name":"펨트론","price":16470,"rate":13.98,"tvEok":28.46,"capEok":3688.0,"isCap":false,"prevClose":14450,"open":14750,"high":16990,"low":14750,"nxt":null,"ot":null},{"code":"007660","name":"이수페타시스","price":103800,"rate":13.07,"tvEok":1712.94,"capEok":76199.0,"isCap":false,"prevClose":91802,"open":95300,"high":107000,"low":95000,"nxt":null,"ot":null}]},{"no":12,"name":"반도체 장비","score":87.5,"aliases":["시스템반도체"],"changeRate":10.24,"rise":91,"steady":1,"fall":3,"total":95,"tradingValueEok":25660.4,"streakDays":2,"recent3d":-2.97,"capCount":1,"naverLeaders":[{"code":"049080","name":"기가레인","rate":29.92},{"code":"122640","name":"예스티","rate":26.25}],"judeokLeaders":[{"code":"319660","name":"피에스케이","price":189400,"rate":24.44,"tvEok":2145.84,"capEok":54863.0,"isCap":false,"prevClose":152202,"open":null,"high":null,"low":null,"nxt":null,"ot":null,"isBigTv":true},{"code":"095610","name":"테스","price":177700,"rate":22.55,"tvEok":1564.17,"capEok":34403.0,"isCap":false,"prevClose":145002,"open":null,"high":null,"low":null,"nxt":null,"ot":null,"isBigTv":true},{"code":"240810","name":"원익IPS","price":125000,"rate":19.16,"tvEok":3610.36,"capEok":61355.0,"isCap":false,"prevClose":104901,"open":null,"high":null,"low":null,"nxt":null,"ot":null,"isBigTv":true}],"stocks":[{"code":"049080","name":"기가레인","price":5970,"rate":29.92,"tvEok":20.45,"capEok":507.0,"isCap":true,"prevClose":4595,"open":4700,"high":5970,"low":4695,"nxt":null,"ot":{"price":5970,"rate":0.0}},{"code":"122640","name":"예스티","price":31500,"rate":26.25,"tvEok":255.39,"capEok":6800.0,"isCap":false,"prevClose":24950,"open":26250,"high":31500,"low":25700,"nxt":null,"ot":{"price":30900,"rate":-1.9}},{"code":"319660","name":"피에스케이","price":189400,"rate":24.44,"tvEok":2145.84,"capEok":54863.0,"isCap":false,"prevClose":152202,"open":161800,"high":195300,"low":157000,"nxt":null,"ot":null},{"code":"417840","name":"저스템","price":12720,"rate":24.34,"tvEok":226.17,"capEok":2909.0,"isCap":false,"prevClose":10230,"open":11000,"high":13050,"low":10900,"nxt":null,"ot":{"price":12680,"rate":-0.31}}]},{"no":269,"name":"LED장비","score":85.7,"aliases":[],"changeRate":13.68,"rise":11,"steady":0,"fall":0,"total":11,"tradingValueEok":6190.0,"streakDays":2,"recent3d":-3.14,"capCount":1,"naverLeaders":[{"code":"049080","name":"기가레인","rate":29.92},{"code":"122640","name":"예스티","rate":26.25}],"judeokLeaders":[{"code":"122640","name":"예스티","price":31500,"rate":26.25,"tvEok":255.39,"capEok":6800.0,"isCap":false,"prevClose":24950,"open":null,"high":null,"low":null,"nxt":null,"ot":null,"isBigTv":false},{"code":"131290","name":"티에스이","price":269500,"rate":20.31,"tvEok":616.19,"capEok":29811.0,"isCap":false,"prevClose":224005,"open":null,"high":null,"low":null,"nxt":null,"ot":null,"isBigTv":false},{"code":"036930","name":"주성엔지니어링","price":191900,"rate":7.57,"tvEok":4193.69,"capEok":89197.0,"isCap":false,"prevClose":178395,"open":null,"high":null,"low":null,"nxt":null,"ot":null,"isBigTv":true}],"stocks":[{"code":"049080","name":"기가레인","price":5970,"rate":29.92,"tvEok":20.45,"capEok":507.0,"isCap":true,"prevClose":4595,"open":4700,"high":5970,"low":4695,"nxt":null,"ot":{"price":5970,"rate":0.0}},{"code":"122640","name":"예스티","price":31500,"rate":26.25,"tvEok":255.39,"capEok":6800.0,"isCap":false,"prevClose":24950,"open":26250,"high":31500,"low":25700,"nxt":null,"ot":{"price":30900,"rate":-1.9}},{"code":"412350","name":"레이저쎌","price":6190,"rate":23.8,"tvEok":140.49,"capEok":904.0,"isCap":false,"prevClose":5000,"open":5200,"high":6400,"low":5090,"nxt":null,"ot":{"price":6150,"rate":-0.65}},{"code":"131290","name":"티에스이","price":269500,"rate":20.31,"tvEok":616.19,"capEok":29811.0,"isCap":false,"prevClose":224005,"open":236000,"high":291000,"low":232000,"nxt":null,"ot":null}]},{"no":92,"name":"통신장비","score":84.2,"aliases":[],"changeRate":9.92,"rise":41,"steady":2,"fall":3,"total":46,"tradingValueEok":2750.2,"streakDays":2,"recent3d":-2.41,"capCount":2,"naverLeaders":[{"code":"049080","name":"기가레인","rate":29.92},{"code":"069540","name":"빛과전자","rate":29.89}],"judeokLeaders":[{"code":"327260","name":"RF머트리얼즈","price":52200,"rate":16.91,"tvEok":169.19,"capEok":4695.0,"isCap":false,"prevClose":44650,"open":null,"high":null,"low":null,"nxt":null,"ot":null,"isBigTv":false},{"code":"069540","name":"빛과전자","price":2325,"rate":29.89,"tvEok":151.37,"capEok":2620.0,"isCap":true,"prevClose":1790,"open":null,"high":null,"low":null,"nxt":null,"ot":null,"isBigTv":false},{"code":"178320","name":"서진시스템","price":47350,"rate":13.55,"tvEok":529.83,"capEok":30139.0,"isCap":false,"prevClose":41700,"open":null,"high":null,"low":null,"nxt":null,"ot":null,"isBigTv":false}],"stocks":[{"code":"049080","name":"기가레인","price":5970,"rate":29.92,"tvEok":20.45,"capEok":507.0,"isCap":true,"prevClose":4595,"open":4700,"high":5970,"low":4695,"nxt":null,"ot":{"price":5970,"rate":0.0}},{"code":"069540","name":"빛과전자","price":2325,"rate":29.89,"tvEok":151.37,"capEok":2620.0,"isCap":true,"prevClose":1790,"open":1825,"high":2325,"low":1825,"nxt":null,"ot":{"price":2325,"rate":0.0}},{"code":"109070","name":"주성코퍼레이션","price":1680,"rate":21.74,"tvEok":62.7,"capEok":887.0,"isCap":false,"prevClose":1380,"open":1500,"high":1790,"low":1500,"nxt":null,"ot":{"price":1702,"rate":1.31}},{"code":"065770","name":"CS","price":1815,"rate":20.2,"tvEok":21.85,"capEok":176.0,"isCap":false,"prevClose":1510,"open":1537,"high":1859,"low":1510,"nxt":null,"ot":{"price":1789,"rate":-1.43}}]},{"no":556,"name":"뉴로모픽 반도체","score":83.3,"aliases":[],"changeRate":9.95,"rise":7,"steady":0,"fall":0,"total":7,"tradingValueEok":58036.4,"streakDays":2,"recent3d":-0.8,"capCount":0,"naverLeaders":[{"code":"445090","name":"에이직랜드","rate":16.82},{"code":"330860","name":"네패스아크","rate":14.06}],"judeokLeaders":[{"code":"330860","name":"네패스아크","price":39750,"rate":14.06,"tvEok":165.33,"capEok":4843.0,"isCap":false,"prevClose":34850,"open":null,"high":null,"low":null,"nxt":null,"ot":null,"isBigTv":false},{"code":"445090","name":"에이직랜드","price":25000,"rate":16.82,"tvEok":122.99,"capEok":2731.0,"isCap":false,"prevClose":21400,"open":null,"high":null,"low":null,"nxt":null,"ot":null,"isBigTv":false},{"code":"005930","name":"삼성전자","price":285000,"rate":2.52,"tvEok":57682.81,"capEok":16661894.0,"isCap":false,"prevClose":277995,"open":null,"high":null,"low":null,"nxt":null,"ot":null,"isBigTv":true}],"stocks":[{"code":"445090","name":"에이직랜드","price":25000,"rate":16.82,"tvEok":122.99,"capEok":2731.0,"isCap":false,"prevClose":21400,"open":21500,"high":26500,"low":20250,"nxt":null,"ot":null},{"code":"330860","name":"네패스아크","price":39750,"rate":14.06,"tvEok":165.33,"capEok":4843.0,"isCap":false,"prevClose":34850,"open":35600,"high":41500,"low":33950,"nxt":null,"ot":{"price":39350,"rate":-1.01}},{"code":"389020","name":"자람테크놀로지","price":23600,"rate":11.85,"tvEok":13.36,"capEok":1630.0,"isCap":false,"prevClose":21100,"open":21150,"high":24550,"low":21150,"nxt":null,"ot":{"price":23600,"rate":0.0}},{"code":"092600","name":"앤씨앤","price":2375,"rate":10.47,"tvEok":1.17,"capEok":119.0,"isCap":false,"prevClose":2150,"open":2150,"high":2395,"low":2145,"nxt":null,"ot":null}]},{"no":536,"name":"HBM(고대역폭메모리)","score":82.7,"aliases":[],"changeRate":10.04,"rise":32,"steady":0,"fall":1,"total":33,"tradingValueEok":170859.2,"streakDays":2,"recent3d":-3.37,"capCount":0,"naverLeaders":[{"code":"122640","name":"예스티","rate":26.25},{"code":"412350","name":"레이저쎌","rate":23.8}],"judeokLeaders":[{"code":"031980","name":"피에스케이홀딩스","price":136200,"rate":18.23,"tvEok":372.54,"capEok":29368.0,"isCap":false,"prevClose":115199,"open":null,"high":null,"low":null,"nxt":null,"ot":null,"isBigTv":false},{"code":"122640","name":"예스티","price":31500,"rate":26.25,"tvEok":255.39,"capEok":6800.0,"isCap":false,"prevClose":24950,"open":null,"high":null,"low":null,"nxt":null,"ot":null,"isBigTv":false},{"code":"281820","name":"케이씨텍","price":97400,"rate":16.65,"tvEok":308.56,"capEok":19284.0,"isCap":false,"prevClose":83498,"open":null,"high":null,"low":null,"nxt":null,"ot":null,"isBigTv":false}],"stocks":[{"code":"122640","name":"예스티","price":31500,"rate":26.25,"tvEok":255.39,"capEok":6800.0,"isCap":false,"prevClose":24950,"open":26250,"high":31500,"low":25700,"nxt":null,"ot":{"price":30900,"rate":-1.9}},{"code":"412350","name":"레이저쎌","price":6190,"rate":23.8,"tvEok":140.49,"capEok":904.0,"isCap":false,"prevClose":5000,"open":5200,"high":6400,"low":5090,"nxt":null,"ot":{"price":6150,"rate":-0.65}},{"code":"031980","name":"피에스케이홀딩스","price":136200,"rate":18.23,"tvEok":372.54,"capEok":29368.0,"isCap":false,"prevClose":115199,"open":120800,"high":141600,"low":117700,"nxt":null,"ot":null},{"code":"281820","name":"케이씨텍","price":97400,"rate":16.65,"tvEok":308.56,"capEok":19284.0,"isCap":false,"prevClose":83498,"open":89500,"high":102100,"low":86100,"nxt":null,"ot":null}]},{"no":14,"name":"반도체 재료/부품","score":81.2,"aliases":[],"changeRate":8.58,"rise":68,"steady":0,"fall":1,"total":69,"tradingValueEok":7114.0,"streakDays":2,"recent3d":-2.21,"capCount":0,"naverLeaders":[{"code":"043590","name":"웰킵스하이텍","rate":23.33},{"code":"077360","name":"덕산하이메탈","rate":20.0}],"judeokLeaders":[{"code":"093370","name":"후성","price":13740,"rate":16.05,"tvEok":1193.89,"capEok":14737.0,"isCap":false,"prevClose":11840,"open":null,"high":null,"low":null,"nxt":null,"ot":null,"isBigTv":true},{"code":"000150","name":"두산","price":1382000,"rate":14.88,"tvEok":1324.4,"capEok":223799.0,"isCap":false,"prevClose":1202994,"open":null,"high":null,"low":null,"nxt":null,"ot":null,"isBigTv":true},{"code":"281820","name":"케이씨텍","price":97400,"rate":16.65,"tvEok":308.56,"capEok":19284.0,"isCap":false,"prevClose":83498,"open":null,"high":null,"low":null,"nxt":null,"ot":null,"isBigTv":false}],"stocks":[{"code":"043590","name":"웰킵스하이텍","price":1475,"rate":23.33,"tvEok":34.46,"capEok":200.0,"isCap":false,"prevClose":1196,"open":1313,"high":1554,"low":1277,"nxt":null,"ot":{"price":1400,"rate":-5.08}},{"code":"077360","name":"덕산하이메탈","price":9540,"rate":20.0,"tvEok":86.99,"capEok":4335.0,"isCap":false,"prevClose":7950,"open":8290,"high":9720,"low":8230,"nxt":null,"ot":{"price":9540,"rate":0.0}},{"code":"311320","name":"지오엘리먼트","price":10580,"rate":19.14,"tvEok":17.15,"capEok":1335.0,"isCap":false,"prevClose":8880,"open":9330,"high":11110,"low":8940,"nxt":null,"ot":{"price":10370,"rate":-1.98}},{"code":"170920","name":"엘티씨","price":50300,"rate":17.8,"tvEok":176.95,"capEok":5314.0,"isCap":false,"prevClose":42699,"open":45000,"high":51300,"low":43600,"nxt":null,"ot":{"price":51300,"rate":1.99}}]}],"crossTotal":110,"crossLeaders":[{"code":"064260","name":"다날","rate":9.8,"price":4370,"count":8,"themes":["NFT(대체불가토큰)","STO(토큰증권 발행)","모바일솔루션(스마트폰)","모바일콘텐츠(스마트폰/태블릿PC)","스테이블코인","음원/음반"],"nxt":null,"ot":{"price":4370,"rate":0.0}},{"code":"067170","name":"오텍","rate":14.81,"price":2830,"count":7,"themes":["고령화 사회(노인복지)","공기청정기","냉각시스템(액침냉각 등)","여름","재난/안전(지진/화재 등)","코로나19(음압병실/음압구급차)"],"nxt":null,"ot":{"price":2805,"rate":-0.88}},{"code":"049080","name":"기가레인","rate":29.92,"price":5970,"count":6,"themes":["5G(5세대 이동통신)","LED장비","갤럭시 부품주","반도체 장비","스마트폰","통신장비"],"nxt":null,"ot":{"price":5970,"rate":0.0}},{"code":"354320","name":"알멕","rate":20.97,"price":31150,"count":6,"themes":["2차전지","2차전지(소재/부품)","리비안(RIVIAN)","비철금속","우주항공산업(누리호/인공위성 등)","전기차"],"nxt":null,"ot":{"price":31050,"rate":-0.32}},{"code":"077360","name":"덕산하이메탈","rate":20.0,"price":9540,"count":6,"themes":["그래핀","드론(Drone)","반도체 기판(FC-BGA/PCB/MLB 등)","반도체 재료/부품","방위산업/전쟁 및 테러","우주항공산업(누리호/인공위성 등)"],"nxt":null,"ot":{"price":9540,"rate":0.0}},{"code":"089890","name":"코세스","rate":19.78,"price":33300,"count":6,"themes":["2차전지","2차전지(장비)","고체산화물 연료전지(SOFC)","마이크로 LED","메타버스(Metaverse)","플렉서블 디스플레이"],"nxt":null,"ot":null},{"code":"036420","name":"콘텐트리중앙","rate":16.92,"price":1520,"count":5,"themes":["미디어(방송/신문)","엔터테인먼트","영상콘텐츠","영화","지주사"],"nxt":null,"ot":{"price":1510,"rate":-0.66}},{"code":"003530","name":"한화투자증권","rate":9.61,"price":4790,"count":5,"themes":["STO(토큰증권 발행)","두나무(Dunamu)","야놀자(Yanolja)","증권","토스(toss)"],"nxt":null,"ot":{"price":4760,"rate":-0.63}},{"code":"078930","name":"GS","rate":6.08,"price":80200,"count":5,"themes":["LPG(액화석유가스)","윤활유","자원개발","정유","주유소"],"nxt":null,"ot":null},{"code":"122640","name":"예스티","rate":26.25,"price":31500,"count":4,"themes":["HBM(고대역폭메모리)","LED장비","OLED(유기 발광 다이오드)","반도체 장비"],"nxt":null,"ot":{"price":30900,"rate":-1.9}},{"code":"043590","name":"웰킵스하이텍","rate":23.33,"price":1475,"count":4,"themes":["OLED(유기 발광 다이오드)","무선충전기술","반도체 재료/부품","스마트폰"],"nxt":null,"ot":{"price":1400,"rate":-5.08}},{"code":"093370","name":"후성","rate":16.05,"price":13740,"count":4,"themes":["日 수출 규제(국산화 등)","리튬","여름","온실가스(탄소배출권)/탄소 포집·활용·저장(CCUS)"],"nxt":null,"ot":{"price":13590,"rate":-1.09}},{"code":"192650","name":"드림텍","rate":11.73,"price":4525,"count":4,"themes":["바이오인식(생체인식)","밸류업(24년 기업가치 제고계획 발표)","코로나19(진단/치료제/백신 개발 등)","코로나19(진단키트)"],"nxt":null,"ot":{"price":4525,"rate":0.0}},{"code":"048530","name":"인트론바이오","rate":11.59,"price":2600,"count":4,"themes":["마이코플라스마 폐렴","마이크로바이옴","백신/진단시약/방역(신종플루, AI 등)","코로나19(진단키트)"],"nxt":null,"ot":{"price":2600,"rate":0.0}},{"code":"032820","name":"우리기술","rate":11.54,"price":11210,"count":4,"themes":["수자원(양적/질적 개선)","원자력발전","원자력발전소 해체","풍력에너지"],"nxt":null,"ot":{"price":11560,"rate":3.12}},{"code":"052400","name":"코나아이","rate":10.46,"price":44900,"count":4,"themes":["삼성페이","인터넷은행","지역화폐","핀테크(FinTech)"],"nxt":null,"ot":null},{"code":"126700","name":"하이비젼시스템","rate":10.02,"price":9990,"count":4,"themes":["3D 프린터","가상현실(VR)","아이폰","카메라모듈/부품"],"nxt":null,"ot":{"price":9900,"rate":-0.9}},{"code":"037710","name":"광주신세계","rate":19.71,"price":49800,"count":3,"themes":["백화점","밸류업(24년 기업가치 제고계획 발표)","소매유통"],"nxt":null,"ot":null},{"code":"085910","name":"네오티스","rate":19.18,"price":17960,"count":3,"themes":["PCB(FPCB 등)","반도체 기판(FC-BGA/PCB/MLB 등)","전기차"],"nxt":null,"ot":{"price":17960,"rate":0.0}},{"code":"006340","name":"대원전선","rate":17.34,"price":11300,"count":3,"themes":["전력설비","전선","철도"],"nxt":null,"ot":{"price":11300,"rate":0.0}}],"extOpen":true}